{
    "id": 13,
    "category": "Relationship & Family",
    "title": "Parenting Through Different Life Stages",
    "theme": "Adapting parenting styles to meet the evolving needs of children from infancy to adolescence",
    "subtopics": [
        "Positive discipline techniques",
        "Supporting emotional development",
        "Balancing screen time and physical activity",
        "Helping with school challenges",
        "Fostering independence",
        "Navigating peer pressure and friendships",
        "Parent-child communication strategies",
        "Maintaining parental self-care"
    ]
}