{
    "id": 9,
    "category": "Deployment/Integration",
    "title": "Production Monitoring, Documentation, and Maintenance Planning",
    "theme": "Establishing monitoring, documentation, and support processes for long-term simulation platform sustainability",
    "subtopics": [
        "Real-time performance and error monitoring",
        "Log aggregation and analysis tools",
        "Incident response and escalation procedures",
        "Comprehensive user and developer documentation",
        "API reference and usage guides",
        "Knowledge transfer sessions and training materials",
        "Maintenance scheduling and update procedures",
        "Support ticketing and feedback systems",
        "Security audits and compliance checks",
        "Roadmap planning for future enhancements"
    ],
    "timeline": "2025-02-16 to 2025-02-28",
    "phase_type": "deployment",
    "development_dates": {
        "main_development_type": "development project",
        "main_development_starts": "2024-08-01",
        "main_development_ends": "2025-01-31",
        "main_development_duration": "6 months",
        "current_phase_relation": "after"
    },
    "phase_boundaries": {
        "can_mention": [
            "monitoring",
            "documentation",
            "maintenance"
        ],
        "cannot_mention": [
            "feature development",
            "core coding",
            "testing"
        ],
        "tense_for_main_development": "past"
    },
    "key_technical_milestones": [
        "Monitoring dashboards and alerts operational",
        "Complete documentation and training delivered",
        "Maintenance and support processes established"
    ],
    "future_technical_references": [
        "Foundation for ongoing platform improvements",
        "Supports user adoption and developer onboarding",
        "Enables proactive issue resolution"
    ],
    "technical_continuity_hooks": [
        "Feeds future development cycles and updates",
        "Ensures platform reliability and user satisfaction",
        "Supports community and stakeholder engagement"
    ]
}