{
    "friends": [
        {
            "id": 253,
            "gender": "female",
            "name": "Heidi",
            "age": 45
        },
        {
            "id": 258,
            "gender": "female",
            "name": "Kaitlin",
            "age": 38
        }
    ],
    "acquaintances": [
        {
            "id": 196,
            "gender": "male",
            "name": "Andrew",
            "age": 10
        },
        {
            "id": 204,
            "gender": "male",
            "name": "John",
            "age": 25
        },
        {
            "id": 216,
            "gender": "male",
            "name": "Matthew",
            "age": 30
        }
    ]
}