{
    "id": 1,
    "category": "Planning/Preparation",
    "title": "Architecture Design and Technology Stack Selection for Simulation Environment",
    "theme": "Designing system architecture and selecting technologies for scalable autonomous driving simulation",
    "subtopics": [
        "High-level system architecture diagrams",
        "Component interaction and data flow design",
        "Selection of 3D engine and rendering technologies",
        "Sensor simulation frameworks evaluation",
        "Choice of programming languages and libraries",
        "Development environment and toolchain setup",
        "Version control and collaboration tools configuration",
        "Preliminary CI/CD pipeline design",
        "Team roles and responsibilities definition",
        "Project timeline and milestone planning"
    ],
    "timeline": "2024-07-16 to 2024-07-31",
    "phase_type": "planning",
    "development_dates": {
        "main_development_type": "development project",
        "main_development_starts": "2024-08-01",
        "main_development_ends": "2025-01-31",
        "main_development_duration": "6 months",
        "current_phase_relation": "before"
    },
    "phase_boundaries": {
        "can_mention": [
            "architecture design",
            "technology evaluation",
            "environment setup"
        ],
        "cannot_mention": [
            "coding core features",
            "deployment",
            "testing"
        ],
        "tense_for_main_development": "future"
    },
    "key_technical_milestones": [
        "Finalized system architecture blueprint",
        "Technology stack and tools approved",
        "Development environment fully configured"
    ],
    "future_technical_references": [
        "Foundation for infrastructure and core development",
        "Baseline for coding standards and integrations",
        "Setup for team collaboration and workflow"
    ],
    "technical_continuity_hooks": [
        "Leads into foundation building and infrastructure setup",
        "Defines technical constraints for initial prototypes",
        "Enables smooth transition to core development"
    ]
}