{
    "id": 9,
    "category": "Trip Planning",
    "title": "Arranging a Luxury Honeymoon in the Maldives",
    "theme": "Creating a dream honeymoon experience",
    "subtopics": [
        "Selecting the perfect luxury resort and room type",
        "Arranging private tours and excursions",
        "Planning romantic dining experiences on the beach or overwater",
        "Choosing spa and wellness treatments for couples",
        "Purchasing comprehensive travel insurance for luxury trips",
        "Planning surprise activities for your partner",
        "Coordinating seaplane or speedboat transfers",
        "Balancing relaxation with adventure activities"
    ],
    "mode": "similar",
    "timeline": "[Start September, 2024 - End November, 2024]"
}